setup.py
cowboy/__init__.py
cowboy/base.py
cowboy/daterange.py
cowboy/numberrange.py
cowboy.egg-info/PKG-INFO
cowboy.egg-info/SOURCES.txt
cowboy.egg-info/dependency_links.txt
cowboy.egg-info/not-zip-safe
cowboy.egg-info/top_level.txt