Metadata-Version: 1.0
Name: cowboy
Version: 1.0.0
Summary: Works on ranges
Home-page: http://github.com/brianhicks/cowboy
Author: Flying Circus
Author-email: brian@brianthicks.com
License: MIT
Platform: UNKNOWN
